lscolumn.py
lscolumn-0.1.2.dist-info/LICENSE
lscolumn-0.1.2.dist-info/METADATA
lscolumn-0.1.2.dist-info/WHEEL
lscolumn-0.1.2.dist-info/top_level.txt
lscolumn-0.1.2.dist-info/RECORD
