Metadata-Version: 2.1
Name: lscolumn
Version: 0.1.2
Summary: Print a list of strings in columns like in `ls`.
Home-page: https://github.com/kkew3/lscolumn
Author: Kaiwen Wu
Author-email: kps6326@hotmail.com
License: MIT
Platform: UNKNOWN
Classifier: License :: OSI Approved :: MIT License
Classifier: Programming Language :: Python :: 3
Requires-Python: >=3.3
License-File: LICENSE
Requires-Dist: cjkjust (>=0.1.4)
